[
  {
    "name": "MetaAccount (v1.0.0)",
    "description": "Initial version of MetaAccount implementation, superseded by v2",
    "code_id": "293",
    "hash": "52373BC3DDA80479DBA7E6B7FE031FFB698141B0289455E4E57F913D46115BCC",
    "governance": "Genesis",
    "release": {
      "url": "https://github.com/burnt-labs/contracts/releases/tag/v1.0.0",
      "version": "v1.0.0"
    },
    "author": {
      "name": "Burnt Labs",
      "url": "https://burnt.com"
    },
    "deprecated": true,
    "network": "xion-testnet-2",
    "mainnet_code_id": "1",
    "deployed_by": "xion1q9lqzpc73fewqva98pwaqvezaf9vqqulw3hmmx",
    "deployed_at": "2025-04-03T19:29:15.817Z"
  },
  {
    "name": "Polytone Proxy",
    "description": "ICA Proxy, allows controlled execution of messages.",
    "code_id": "294",
    "hash": "78B5608D3005889DC009DFB092818AFF8D08FEBE9E87D0550B26A2B907E27D81",
    "release": {
      "url": "https://github.com/DA0-DA0/polytone/releases/tag/v1.1.0",
      "version": "v1.1.0"
    },
    "author": {
      "name": "DAO DAO",
      "url": "https://daodao.zone/"
    },
    "governance": "Genesis",
    "deprecated": false,
    "network": "xion-testnet-2",
    "mainnet_code_id": "2",
    "deployed_by": "xion1q9lqzpc73fewqva98pwaqvezaf9vqqulw3hmmx",
    "deployed_at": "2025-04-03T19:29:20.078Z"
  },
  {
    "name": "Polytone Voice",
    "description": "Receiver of messages over IBC, executes on the destination chain. Maintains access control through the proxy (see above).",
    "code_id": "295",
    "hash": "C91EEFB0ED7F1A6255ED1F82569DD411F62BF88213DF7821CF73EE747E75D3F4",
    "release": {
      "url": "https://github.com/DA0-DA0/polytone/releases/tag/v1.1.0",
      "version": "v1.1.0"
    },
    "author": {
      "name": "DAO DAO",
      "url": "https://daodao.zone/"
    },
    "governance": "Genesis",
    "deprecated": false,
    "network": "xion-testnet-2",
    "mainnet_code_id": "3",
    "deployed_by": "xion1q9lqzpc73fewqva98pwaqvezaf9vqqulw3hmmx",
    "deployed_at": "2025-04-03T19:29:25.370Z"
  },
  {
    "name": "Polytone Note",
    "description": "Sends messages to be executed on other chains over IBC. Handles channel management and packet routing.",
    "code_id": "296",
    "hash": "D497DDFF42C93FD95A1AD41C1BB63286B9772C5C0163955C9B9BABFF405FCCD0",
    "release": {
      "url": "https://github.com/DA0-DA0/polytone/releases/tag/v1.1.0",
      "version": "v1.1.0"
    },
    "author": {
      "name": "DAO DAO",
      "url": "https://daodao.zone/"
    },
    "governance": "Genesis",
    "deprecated": false,
    "network": "xion-testnet-2",
    "mainnet_code_id": "4",
    "deployed_by": "xion1q9lqzpc73fewqva98pwaqvezaf9vqqulw3hmmx",
    "deployed_at": "2025-04-03T19:29:30.369Z"
  },
  {
    "name": "MetaAccount (v2)",
    "description": "Second version of Xion's MetaAccount implementation",
    "code_id": "297",
    "hash": "4D11BBE122FE599E0C5DB2DE26B9F7DB4110AC50C88BD63E98EE8D31C02B06FB",
    "release": {
      "url": "https://github.com/burnt-labs/contracts/pull/40",
      "version": "pr40"
    },
    "author": {
      "name": "Burnt Labs",
      "url": "https://burnt.com"
    },
    "governance": "Genesis",
    "deprecated": false,
    "network": "xion-testnet-2",
    "mainnet_code_id": "5",
    "deployed_by": "xion1q9lqzpc73fewqva98pwaqvezaf9vqqulw3hmmx",
    "deployed_at": "2025-04-03T19:29:35.156Z"
  },
  {
    "name": "cw1 Subkeys",
    "description": "A Proxy contract that extends the functionality of cw1-whitelist. Allows admins to grant allowances and set permissions to 'subkeys'",
    "code_id": "298",
    "hash": "6CB636F6AF214E54454F8ABC4F643748CDD89F9A4E868638E722729987D1F808",
    "release": {
      "url": "https://github.com/CosmWasm/cw-plus/releases/tag/v2.0.0",
      "version": "v2.0.0"
    },
    "author": {
      "name": "CosmWasm",
      "url": "https://cosmwasm.com/"
    },
    "governance": "Genesis",
    "deprecated": false,
    "network": "xion-testnet-2",
    "mainnet_code_id": "6",
    "deployed_by": "xion1q9lqzpc73fewqva98pwaqvezaf9vqqulw3hmmx",
    "deployed_at": "2025-04-03T19:29:39.911Z"
  },
  {
    "name": "cw1 Whitelist",
    "description": "Proxy contract maintaining a list of admin addresses that can execute messages through it. Admin list defined at contract creation.",
    "code_id": "299",
    "hash": "F0B99C3B58AA3620204827E861C2166AE5B78392075786777A20A34DB83EA261",
    "release": {
      "url": "https://github.com/CosmWasm/cw-plus/releases/tag/v2.0.0",
      "version": "v2.0.0"
    },
    "author": {
      "name": "CosmWasm",
      "url": "https://cosmwasm.com/"
    },
    "governance": "Genesis",
    "deprecated": false,
    "network": "xion-testnet-2",
    "mainnet_code_id": "7",
    "deployed_by": "xion1q9lqzpc73fewqva98pwaqvezaf9vqqulw3hmmx",
    "deployed_at": "2025-04-03T19:29:44.598Z"
  },
  {
    "name": "cw3 Fixed Multisig",
    "description": "Implements a multisig wallet with a fixed set of voters defined at instantiation, each voter can have different voting weights. Allows voters to create, vote on, and execute proposals containing arbitrary messages. Supports different voting thresholds & configurable voting periods.",
    "code_id": "300",
    "hash": "080973861FE360219A81602C413054B4427CDE4623D0B72B83BD89A24579C8D3",
    "release": {
      "url": "https://github.com/CosmWasm/cw-plus/releases/tag/v2.0.0",
      "version": "v2.0.0"
    },
    "author": {
      "name": "CosmWasm",
      "url": "https://cosmwasm.com/"
    },
    "governance": "Genesis",
    "deprecated": false,
    "network": "xion-testnet-2",
    "mainnet_code_id": "8",
    "deployed_by": "xion1q9lqzpc73fewqva98pwaqvezaf9vqqulw3hmmx",
    "deployed_at": "2025-04-03T19:29:49.370Z"
  },
  {
    "name": "cw3 Flex Multisig",
    "description": "An advanced multisig using a separate cw4 (group) contract to manage its voter set, allowing multiple multisigs to share the same group of voters with different voting thresholds.",
    "code_id": "301",
    "hash": "157C19929BF4DE3331310CA2A0FDF4F64F04B700E06C7674DAE0D28EB9F8B88E",
    "release": {
      "url": "https://github.com/CosmWasm/cw-plus/releases/tag/v2.0.0",
      "version": "v2.0.0"
    },
    "author": {
      "name": "CosmWasm",
      "url": "https://cosmwasm.com/"
    },
    "governance": "Genesis",
    "deprecated": false,
    "network": "xion-testnet-2",
    "mainnet_code_id": "9",
    "deployed_by": "xion1q9lqzpc73fewqva98pwaqvezaf9vqqulw3hmmx",
    "deployed_at": "2025-04-03T19:29:54.261Z"
  },
  {
    "name": "cw4 Group",
    "description": "Manages group membership with weighted voting power. Maintains a list of members, controlled by an admin with rights to add or remove members.",
    "code_id": "302",
    "hash": "DB967DF6E55B8E61CA535020B108239A14E2477793CC8A389BB78A0FB51956B6",
    "release": {
      "url": "https://github.com/CosmWasm/cw-plus/releases/tag/v2.0.0",
      "version": "v2.0.0"
    },
    "author": {
      "name": "CosmWasm",
      "url": "https://cosmwasm.com/"
    },
    "governance": "Genesis",
    "deprecated": false,
    "network": "xion-testnet-2",
    "mainnet_code_id": "10",
    "deployed_by": "xion1q9lqzpc73fewqva98pwaqvezaf9vqqulw3hmmx",
    "deployed_at": "2025-04-03T19:29:58.938Z"
  },
  {
    "name": "cw4 Stake",
    "description": "cw4 Stake",
    "code_id": "303",
    "hash": "5B10DECC518DDD33510E50935F21914EDFFE966FB4CF976565139C7CB61B4FC6",
    "governance": "Genesis",
    "deprecated": true,
    "release": {
      "url": "https://github.com/CosmWasm/cw-plus/releases/tag/v2.0.0",
      "version": "v2.0.0"
    },
    "author": {
      "name": "CosmWasm",
      "url": "https://cosmwasm.com/"
    },
    "network": "xion-testnet-2",
    "mainnet_code_id": "11",
    "deployed_by": "xion1q9lqzpc73fewqva98pwaqvezaf9vqqulw3hmmx",
    "deployed_at": "2025-04-03T19:30:03.635Z"
  },
  {
    "name": "cw4 Stake",
    "description": "Determines group membership and voting weights based on the amount of tokens (native or cw20) that users have staked, with configurable parameters like minimum bond amount and tokens-per-weight ratio.",
    "code_id": "304",
    "hash": "428F42A8ECE687403DD85D0145E44D9F7AAD9F40AB8BAECAD9892EEA7DBE6301",
    "release": {
      "url": "https://github.com/CosmWasm/cw-plus/releases/tag/v2.0.0",
      "version": "v2.0.0"
    },
    "author": {
      "name": "CosmWasm",
      "url": "https://cosmwasm.com/"
    },
    "governance": "Genesis",
    "deprecated": false,
    "network": "xion-testnet-2",
    "mainnet_code_id": "12",
    "deployed_by": "xion1q9lqzpc73fewqva98pwaqvezaf9vqqulw3hmmx",
    "deployed_at": "2025-04-03T19:30:08.295Z"
  },
  {
    "name": "cw20 Base",
    "description": "Implementation of the CW20 token standard in CosmWasm.",
    "code_id": "305",
    "hash": "346BA91A891F154865EC0C47A66E8C8F645A395E82BEC909AA0EEB417A56C9DB",
    "release": {
      "url": "https://github.com/CosmWasm/cw-plus/releases/tag/v2.0.0",
      "version": "v2.0.0"
    },
    "author": {
      "name": "CosmWasm",
      "url": "https://cosmwasm.com/"
    },
    "governance": "Genesis",
    "deprecated": false,
    "network": "xion-testnet-2",
    "mainnet_code_id": "13",
    "deployed_by": "xion1q9lqzpc73fewqva98pwaqvezaf9vqqulw3hmmx",
    "deployed_at": "2025-04-03T19:30:13.124Z"
  },
  {
    "name": "cw20 ics20",
    "description": "Enables CW20 tokens to be sent over IBC using the ICS20 protocol, allowing custom CW20 tokens from one chain to be used like native tokens on other chains.",
    "code_id": "306",
    "hash": "A8C3BC12D5A7D5DECDB197E4D2443FB85ED69158DA834ED11FF32B7E4B2ABCEA",
    "release": {
      "url": "https://github.com/CosmWasm/cw-plus/releases/tag/v2.0.0",
      "version": "v2.0.0"
    },
    "author": {
      "name": "CosmWasm",
      "url": "https://cosmwasm.com/"
    },
    "governance": "Genesis",
    "deprecated": false,
    "network": "xion-testnet-2",
    "mainnet_code_id": "14",
    "deployed_by": "xion1q9lqzpc73fewqva98pwaqvezaf9vqqulw3hmmx",
    "deployed_at": "2025-04-03T19:30:17.983Z"
  },
  {
    "name": "Treasury",
    "description": "Treasury",
    "code_id": "307",
    "hash": "F3C9748CF3EE391C5E37E91B34785B297F3C2452EDD52B65195BEDD3BF088A7A",
    "release": {
      "url": "https://github.com/burnt-labs/contracts/commit/8224140b66da51fcdef25227a195d2dee16cc422",
      "version": "v0.1.0"
    },
    "author": {
      "name": "Burnt Labs",
      "url": "https://burnt.com"
    },
    "governance": "Genesis",
    "deprecated": false,
    "network": "xion-testnet-2",
    "mainnet_code_id": "15",
    "deployed_by": "xion1q9lqzpc73fewqva98pwaqvezaf9vqqulw3hmmx",
    "deployed_at": "2025-04-03T19:30:22.934Z"
  },
  {
    "name": "Abstract Account",
    "description": "Abstract Account",
    "code_id": "308",
    "hash": "34BD199870A3E4B32ECCCBB9AB66036B85C27AA4A97135CE7491543AF7F8BDA2",
    "release": {
      "url": "https://github.com/AbstractSDK/abstract/releases/tag/v0.25.0",
      "version": "v0.25.0"
    },
    "author": {
      "name": "Abstract Money",
      "url": "https://abstract.money/"
    },
    "governance": "Genesis",
    "deprecated": false,
    "network": "xion-testnet-2",
    "mainnet_code_id": "16",
    "deployed_by": "xion1q9lqzpc73fewqva98pwaqvezaf9vqqulw3hmmx",
    "deployed_at": "2025-04-03T19:30:28.044Z"
  },
  {
    "name": "Abstract Acccount (XION)",
    "description": "Abstract Acccount (XION)",
    "code_id": "309",
    "hash": "2EB73153A5E1B22314E197878DD8F7ED87DFAB2723648C3E47345C6BAD7AC499",
    "release": {
      "url": "https://github.com/AbstractSDK/abstract/releases/tag/v0.25.0",
      "version": "v0.25.0"
    },
    "author": {
      "name": "Abstract Money",
      "url": "https://abstract.money/"
    },
    "governance": "Genesis",
    "deprecated": false,
    "network": "xion-testnet-2",
    "mainnet_code_id": "17",
    "deployed_by": "xion1q9lqzpc73fewqva98pwaqvezaf9vqqulw3hmmx",
    "deployed_at": "2025-04-03T19:30:33.344Z"
  },
  {
    "name": "Abstract ANS Host",
    "description": "Abstract ANS Host",
    "code_id": "310",
    "hash": "F7ED4A2475663583C759437F023C6A5520BA5AAA1EAB3F9AC9B5A43E56528448",
    "governance": "Genesis",
    "release": {
      "url": "https://github.com/AbstractSDK/abstract/releases/tag/v0.25.0",
      "version": "v0.25.0"
    },
    "author": {
      "name": "Abstract Money",
      "url": "https://abstract.money/"
    },
    "deprecated": false,
    "network": "xion-testnet-2",
    "mainnet_code_id": "18",
    "deployed_by": "xion1q9lqzpc73fewqva98pwaqvezaf9vqqulw3hmmx",
    "deployed_at": "2025-04-03T19:30:38.079Z"
  },
  {
    "name": "Abstract IBC Client",
    "description": "Abstract IBC Client",
    "code_id": "311",
    "hash": "FB818D44C51BB71D8BC0307A506E868491771591D7FC3D3F54B0063867DC0EE3",
    "governance": "Genesis",
    "release": {
      "url": "https://github.com/AbstractSDK/abstract/releases/tag/v0.25.0",
      "version": "v0.25.0"
    },
    "author": {
      "name": "Abstract Money",
      "url": "https://abstract.money/"
    },
    "deprecated": false,
    "network": "xion-testnet-2",
    "mainnet_code_id": "19",
    "deployed_by": "xion1q9lqzpc73fewqva98pwaqvezaf9vqqulw3hmmx",
    "deployed_at": "2025-04-03T19:30:42.938Z"
  },
  {
    "name": "Abstract IBC Host",
    "description": "Abstract IBC Host",
    "code_id": "312",
    "hash": "D226765749C500D77AEC51FF3AF4F535606255BCAFB35D2962BA9C0D93F1F4A4",
    "governance": "Genesis",
    "release": {
      "url": "https://github.com/AbstractSDK/abstract/releases/tag/v0.25.0",
      "version": "v0.25.0"
    },
    "author": {
      "name": "Abstract Money",
      "url": "https://abstract.money/"
    },
    "deprecated": false,
    "network": "xion-testnet-2",
    "mainnet_code_id": "20",
    "deployed_by": "xion1q9lqzpc73fewqva98pwaqvezaf9vqqulw3hmmx",
    "deployed_at": "2025-04-03T19:30:47.817Z"
  },
  {
    "name": "Abstract ICA Client",
    "description": "Abstract ICA Client",
    "code_id": "313",
    "hash": "5E3DB897470442C11757216BEDB3991C72244D23BBAE883330AB49AEC99FF284",
    "governance": "Genesis",
    "release": {
      "url": "https://github.com/AbstractSDK/abstract/releases/tag/v0.25.0",
      "version": "v0.25.0"
    },
    "author": {
      "name": "Abstract Money",
      "url": "https://abstract.money/"
    },
    "deprecated": false,
    "network": "xion-testnet-2",
    "mainnet_code_id": "21",
    "deployed_by": "xion1q9lqzpc73fewqva98pwaqvezaf9vqqulw3hmmx",
    "deployed_at": "2025-04-03T19:30:52.407Z"
  },
  {
    "name": "Abstract Module Factory",
    "description": "Abstract Module Factory",
    "code_id": "314",
    "hash": "53733DADE96018B9298B0F2FDB7AF4D1CB7701C59F9ADA518581C2595D7DBDCD",
    "governance": "Genesis",
    "release": {
      "url": "https://github.com/AbstractSDK/abstract/releases/tag/v0.25.0",
      "version": "v0.25.0"
    },
    "author": {
      "name": "Abstract Money",
      "url": "https://abstract.money/"
    },
    "deprecated": false,
    "network": "xion-testnet-2",
    "mainnet_code_id": "22",
    "deployed_by": "xion1q9lqzpc73fewqva98pwaqvezaf9vqqulw3hmmx",
    "deployed_at": "2025-04-03T19:30:57.148Z"
  },
  {
    "name": "Abstract Registry",
    "description": "Abstract Registry",
    "code_id": "315",
    "hash": "133721093CC02A8D7EA5871F532E94EED72B7ED3569435836D1E5198ED549545",
    "governance": "Genesis",
    "release": {
      "url": "https://github.com/AbstractSDK/abstract/releases/tag/v0.25.0",
      "version": "v0.25.0"
    },
    "author": {
      "name": "Abstract Money",
      "url": "https://abstract.money/"
    },
    "deprecated": false,
    "network": "xion-testnet-2",
    "mainnet_code_id": "23",
    "deployed_by": "xion1q9lqzpc73fewqva98pwaqvezaf9vqqulw3hmmx",
    "deployed_at": "2025-04-03T19:31:02.129Z"
  },
  {
    "name": "Multiquery",
    "description": "Multiquery",
    "code_id": "316",
    "hash": "ADF9837667E9C8B21230B96BB81CE1C8024A349073B40242CE441DD8055261E8",
    "governance": "Genesis",
    "release": {
      "url": "https://github.com/AbstractSDK/multiquery/commit/ae6b4225c9a3086a4f353522f5b03343138b16e1",
      "version": "ae6b422"
    },
    "author": {
      "name": "Abstract Money",
      "url": "https://abstract.money/"
    },
    "deprecated": false,
    "network": "xion-testnet-2",
    "mainnet_code_id": "24",
    "deployed_by": "xion1q9lqzpc73fewqva98pwaqvezaf9vqqulw3hmmx",
    "deployed_at": "2025-04-03T19:31:06.572Z"
  },
  {
    "name": "cw721 Base",
    "description": "cw721 Base",
    "code_id": "317",
    "hash": "433D876C396A4836B8F87DC7E9BDE2856DD556270C5E17C7A9D1CCB667657B04",
    "governance": "Genesis",
    "release": {
      "url": "https://github.com/public-awesome/cw-nfts/releases/tag/v0.19.0",
      "version": "v0.19.0"
    },
    "author": {
      "name": "CosmWasm",
      "url": "https://cosmwasm.com/"
    },
    "deprecated": false,
    "network": "xion-testnet-2",
    "mainnet_code_id": "25",
    "deployed_by": "xion1q9lqzpc73fewqva98pwaqvezaf9vqqulw3hmmx",
    "deployed_at": "2025-04-03T19:31:11.486Z"
  },
  {
    "name": "cw721 Expiration",
    "description": "cw721 Expiration",
    "code_id": "318",
    "hash": "A323CFF6A75E00FBB29D2E14CDD9CFF1633E7C2E496A3FB2421CFB3F5CD2475A",
    "governance": "Genesis",
    "release": {
      "url": "https://github.com/public-awesome/cw-nfts/releases/tag/v0.19.0",
      "version": "v0.19.0"
    },
    "author": {
      "name": "CosmWasm",
      "url": "https://cosmwasm.com/"
    },
    "deprecated": false,
    "network": "xion-testnet-2",
    "mainnet_code_id": "26",
    "deployed_by": "xion1q9lqzpc73fewqva98pwaqvezaf9vqqulw3hmmx",
    "deployed_at": "2025-04-03T19:31:16.697Z"
  },
  {
    "name": "cw721 Fixed Price",
    "description": "cw721 Fixed Price",
    "code_id": "319",
    "hash": "D020F5C247ECC12B1C3F7FAA5875CDEF1B746CD004E6A7CF8DBB6E885AA38953",
    "governance": "Genesis",
    "release": {
      "url": "https://github.com/public-awesome/cw-nfts/releases/tag/v0.19.0",
      "version": "v0.19.0"
    },
    "author": {
      "name": "CosmWasm",
      "url": "https://cosmwasm.com/"
    },
    "deprecated": false,
    "network": "xion-testnet-2",
    "mainnet_code_id": "27",
    "deployed_by": "xion1q9lqzpc73fewqva98pwaqvezaf9vqqulw3hmmx",
    "deployed_at": "2025-04-03T19:31:21.261Z"
  },
  {
    "name": "cw721 Metadata Onchain",
    "description": "cw721 Metadata Onchain",
    "code_id": "320",
    "hash": "4A0C08E77AD781BBBB24B08FA4C9DBDA075538C0690AFEB085A9BC9717307B91",
    "governance": "Genesis",
    "release": {
      "url": "https://github.com/public-awesome/cw-nfts/releases/tag/v0.19.0",
      "version": "v0.19.0"
    },
    "author": {
      "name": "CosmWasm",
      "url": "https://cosmwasm.com/"
    },
    "deprecated": false,
    "network": "xion-testnet-2",
    "mainnet_code_id": "28",
    "deployed_by": "xion1q9lqzpc73fewqva98pwaqvezaf9vqqulw3hmmx",
    "deployed_at": "2025-04-03T19:31:26.097Z"
  },
  {
    "name": "cw721 Non-Transferable",
    "description": "cw721 Non-Transferable",
    "code_id": "321",
    "hash": "5F84BC8891ADECD3A14E29A90FCC293B93E25CB7C5E4A7EB4FD4F8E162950E2E",
    "governance": "Genesis",
    "release": {
      "url": "https://github.com/public-awesome/cw-nfts/releases/tag/v0.19.0",
      "version": "v0.19.0"
    },
    "author": {
      "name": "CosmWasm",
      "url": "https://cosmwasm.com/"
    },
    "deprecated": false,
    "network": "xion-testnet-2",
    "mainnet_code_id": "29",
    "deployed_by": "xion1q9lqzpc73fewqva98pwaqvezaf9vqqulw3hmmx",
    "deployed_at": "2025-04-03T19:31:31.051Z"
  },
  {
    "name": "cw721 Receiver Tester",
    "description": "cw721 Receiver Tester",
    "code_id": "322",
    "hash": "42BF86028064EF873F86D857E88E35F21F395655DEB85D5AF047E120B4CCC10A",
    "governance": "Genesis",
    "release": {
      "url": "https://github.com/public-awesome/cw-nfts/releases/tag/v0.19.0",
      "version": "v0.19.0"
    },
    "author": {
      "name": "CosmWasm",
      "url": "https://cosmwasm.com/"
    },
    "deprecated": false,
    "network": "xion-testnet-2",
    "mainnet_code_id": "30",
    "deployed_by": "xion1q9lqzpc73fewqva98pwaqvezaf9vqqulw3hmmx",
    "deployed_at": "2025-04-03T19:31:35.406Z"
  },
  {
    "name": "cw2981 Royalties",
    "description": "cw2981 Royalties",
    "code_id": "323",
    "hash": "49DFD2A8881A2A3811D1DFD2F6EE0E9F221AC22F9E489017B18FB50425DEA0C9",
    "governance": "Genesis",
    "release": {
      "url": "https://github.com/public-awesome/cw-nfts/releases/tag/v0.19.0",
      "version": "v0.19.0"
    },
    "author": {
      "name": "CosmWasm",
      "url": "https://cosmwasm.com/"
    },
    "deprecated": false,
    "network": "xion-testnet-2",
    "mainnet_code_id": "31",
    "deployed_by": "xion1q9lqzpc73fewqva98pwaqvezaf9vqqulw3hmmx",
    "deployed_at": "2025-04-03T19:31:40.304Z"
  },
  {
    "name": "Mercle Mint with Claim",
    "description": "Mercle Mint with Claim",
    "code_id": "324",
    "hash": "D5334D91A6F9B3A2AFFAC914E5CABFABA420EAA08B514BABD66A7D1610373005",
    "governance": "Genesis",
    "release": {
      "url": "https://github.com/mercledao/MercleCosmwasmContracts/commit/18ceaf7e1a57a1dbf189da6e3a173618d4ea64fa",
      "version": "18ceaf7"
    },
    "author": {
      "name": "Mercle",
      "url": "https://mercle.xyz/"
    },
    "deprecated": false,
    "network": "xion-testnet-2",
    "mainnet_code_id": "32",
    "deployed_by": "xion1q9lqzpc73fewqva98pwaqvezaf9vqqulw3hmmx",
    "deployed_at": "2025-04-03T19:31:44.831Z"
  },
  {
    "name": "Mercle NFT Membership",
    "description": "Mercle NFT Membership",
    "code_id": "325",
    "hash": "8F2797B721FA6A27BB8877825AE4E4A790B3E74928F2917E93D221C8EFA7F27C",
    "governance": "Genesis",
    "release": {
      "url": "https://github.com/mercledao/MercleCosmwasmContracts/commit/18ceaf7e1a57a1dbf189da6e3a173618d4ea64fa",
      "version": "18ceaf7"
    },
    "author": {
      "name": "Mercle",
      "url": "https://mercle.xyz/"
    },
    "deprecated": false,
    "network": "xion-testnet-2",
    "mainnet_code_id": "33",
    "deployed_by": "xion1q9lqzpc73fewqva98pwaqvezaf9vqqulw3hmmx",
    "deployed_at": "2025-04-03T19:31:49.422Z"
  },
  {
    "name": "BonusBlock Badge Minter",
    "description": "BonusBlock Badge Minter",
    "code_id": "326",
    "hash": "BC24DEB40C64558643EF52134D7B7D2842BBFA829C698D2F76E72B06318EB95F",
    "governance": "Genesis",
    "release": {
      "url": "https://github.com/BBlockLabs/BonusBlock-Minter-SC-Rust/commit/202538de73d52f0ff66a8e2abb9baaad4ee98053",
      "version": "202538d"
    },
    "author": {
      "name": "BonusBlock",
      "url": "https://www.bonusblock.io/"
    },
    "deprecated": false,
    "network": "xion-testnet-2",
    "mainnet_code_id": "34",
    "deployed_by": "xion1q9lqzpc73fewqva98pwaqvezaf9vqqulw3hmmx",
    "deployed_at": "2025-04-03T19:31:53.997Z"
  },
  {
    "name": "Talis Collection Offer",
    "description": "Talis Collection Offer",
    "code_id": "327",
    "hash": "EBAB20DCEC5D287633C32B224D807B19D52E240F5D233973AB62DBD0CB0C8869",
    "governance": "Genesis",
    "release": {
      "url": "https://github.com/Talis-Art/talis_contracts_v2/commit/f084f5b7950f911b16090dfd38e1c06a177a1da8",
      "version": "f084f5b"
    },
    "author": {
      "name": "Talis",
      "url": "https://talis.art/"
    },
    "deprecated": false,
    "network": "xion-testnet-2",
    "mainnet_code_id": "35",
    "deployed_by": "xion1q9lqzpc73fewqva98pwaqvezaf9vqqulw3hmmx",
    "deployed_at": "2025-04-03T19:31:58.922Z"
  },
  {
    "name": "Talis English Auction",
    "description": "Talis English Auction",
    "code_id": "328",
    "hash": "1323E63BA952BADC880DDB722FCE643DCF6A8C9CAD95B3B6613B111B9DB3FBEA",
    "governance": "Genesis",
    "release": {
      "url": "https://github.com/Talis-Art/talis_contracts_v2/commit/f084f5b7950f911b16090dfd38e1c06a177a1da8",
      "version": "f084f5b"
    },
    "author": {
      "name": "Talis",
      "url": "https://talis.art/"
    },
    "deprecated": false,
    "network": "xion-testnet-2",
    "mainnet_code_id": "36",
    "deployed_by": "xion1q9lqzpc73fewqva98pwaqvezaf9vqqulw3hmmx",
    "deployed_at": "2025-04-03T19:32:03.603Z"
  },
  {
    "name": "Talis Marketplace",
    "description": "Talis Marketplace",
    "code_id": "329",
    "hash": "5F6550AFA2471644849B85DBDC253096656EC00220BD5B53973EBD5E7D40E681",
    "governance": "Genesis",
    "release": {
      "url": "https://github.com/Talis-Art/talis_contracts_v2/commit/f084f5b7950f911b16090dfd38e1c06a177a1da8",
      "version": "f084f5b"
    },
    "author": {
      "name": "Talis",
      "url": "https://talis.art/"
    },
    "deprecated": false,
    "network": "xion-testnet-2",
    "mainnet_code_id": "37",
    "deployed_by": "xion1q9lqzpc73fewqva98pwaqvezaf9vqqulw3hmmx",
    "deployed_at": "2025-04-03T19:32:08.281Z"
  },
  {
    "name": "Talis Multi-Flavor",
    "description": "Talis Multi-Flavor",
    "code_id": "330",
    "hash": "E96FC3039C6F996AE534EE139455213DC976C28F91BF338072C5DB9707C09E9F",
    "governance": "Genesis",
    "release": {
      "url": "https://github.com/Talis-Art/talis_contracts_v2/commit/f084f5b7950f911b16090dfd38e1c06a177a1da8",
      "version": "f084f5b"
    },
    "author": {
      "name": "Talis",
      "url": "https://talis.art/"
    },
    "deprecated": false,
    "network": "xion-testnet-2",
    "mainnet_code_id": "38",
    "deployed_by": "xion1q9lqzpc73fewqva98pwaqvezaf9vqqulw3hmmx",
    "deployed_at": "2025-04-03T19:32:13.051Z"
  },
  {
    "name": "Talis PoC Candy Mint",
    "description": "Talis PoC Candy Mint",
    "code_id": "331",
    "hash": "36E84DB207D0C5B397466296BAE5716C746750E616114D09132DC7FEEC41A6AF",
    "governance": "Genesis",
    "release": {
      "url": "https://github.com/Talis-Art/talis_contracts_v2/commit/f084f5b7950f911b16090dfd38e1c06a177a1da8",
      "version": "f084f5b"
    },
    "author": {
      "name": "Talis",
      "url": "https://talis.art/"
    },
    "deprecated": false,
    "network": "xion-testnet-2",
    "mainnet_code_id": "40",
    "deployed_by": "xion1q9lqzpc73fewqva98pwaqvezaf9vqqulw3hmmx",
    "deployed_at": "2025-04-03T19:32:17.652Z"
  },
  {
    "name": "Talis Xion Proxy",
    "description": "Talis Xion Proxy",
    "code_id": "332",
    "hash": "322FF977502D5CEBE795BC3190826EBCBB79D11DB5822C3BA4D29F935ECEFBF9",
    "governance": "Genesis",
    "release": {
      "url": "https://github.com/Talis-Art/talis_contracts_v2/commit/f084f5b7950f911b16090dfd38e1c06a177a1da8",
      "version": "f084f5b"
    },
    "author": {
      "name": "Talis",
      "url": "https://talis.art/"
    },
    "deprecated": false,
    "network": "xion-testnet-2",
    "mainnet_code_id": "41",
    "deployed_by": "xion1q9lqzpc73fewqva98pwaqvezaf9vqqulw3hmmx",
    "deployed_at": "2025-04-03T19:32:22.082Z"
  },
  {
    "name": "Astroport Factory",
    "description": "Astroport Factory",
    "code_id": "333",
    "hash": "519584219D1E6ABBE84550BAB59A882AC73BA18917ACCB1D0798CD2D269BC607",
    "governance": "Genesis",
    "release": {
      "url": "https://github.com/astroport-fi/astroport-core/releases/tag/v5.7.0",
      "version": "v5.7.0"
    },
    "author": {
      "name": "Astroport",
      "url": "https://astroport.fi/"
    },
    "deprecated": false,
    "network": "xion-testnet-2",
    "mainnet_code_id": "42",
    "deployed_by": "xion1q9lqzpc73fewqva98pwaqvezaf9vqqulw3hmmx",
    "deployed_at": "2025-04-03T19:32:26.745Z"
  },
  {
    "name": "Astroport Maker",
    "description": "Astroport Maker",
    "code_id": "334",
    "hash": "E0894F8A392FA30752DD9E915276A66B9BFF2542538540597913A9230FAC9D15",
    "governance": "Genesis",
    "release": {
      "url": "https://github.com/astroport-fi/astroport-core/releases/tag/v5.7.0",
      "version": "v5.7.0"
    },
    "author": {
      "name": "Astroport",
      "url": "https://astroport.fi/"
    },
    "deprecated": false,
    "network": "xion-testnet-2",
    "mainnet_code_id": "43",
    "deployed_by": "xion1q9lqzpc73fewqva98pwaqvezaf9vqqulw3hmmx",
    "deployed_at": "2025-04-03T19:32:31.397Z"
  },
  {
    "name": "Astroport Native Coin Registry",
    "description": "Astroport Native Coin Registry",
    "code_id": "335",
    "hash": "651DBFA69BBA42437FE70C095AFF1399729366655AC4D584E1F01AA1663E4755",
    "governance": "Genesis",
    "release": {
      "url": "https://github.com/astroport-fi/astroport-core/releases/tag/v5.7.0",
      "version": "v5.7.0"
    },
    "author": {
      "name": "Astroport",
      "url": "https://astroport.fi/"
    },
    "deprecated": false,
    "network": "xion-testnet-2",
    "mainnet_code_id": "44",
    "deployed_by": "xion1q9lqzpc73fewqva98pwaqvezaf9vqqulw3hmmx",
    "deployed_at": "2025-04-03T19:32:36.030Z"
  },
  {
    "name": "Astroport Pair",
    "description": "Astroport Pair",
    "code_id": "336",
    "hash": "0C8F539B9DB7BBA4ADDFC70723712272FD9CC4A53D368D61EA686FC9F59817F2",
    "governance": "Genesis",
    "release": {
      "url": "https://github.com/astroport-fi/astroport-core/releases/tag/v5.7.0",
      "version": "v5.7.0"
    },
    "author": {
      "name": "Astroport",
      "url": "https://astroport.fi/"
    },
    "deprecated": false,
    "network": "xion-testnet-2",
    "mainnet_code_id": "45",
    "deployed_by": "xion1q9lqzpc73fewqva98pwaqvezaf9vqqulw3hmmx",
    "deployed_at": "2025-04-03T19:32:40.819Z"
  },
  {
    "name": "Astroport Router",
    "description": "Astroport Router",
    "code_id": "337",
    "hash": "E4ED3DFC6D8B546ED3BFFFA6181C453EEFD327271AC6CA75DF5483EB596597CE",
    "governance": "Genesis",
    "release": {
      "url": "https://github.com/astroport-fi/astroport-core/releases/tag/v5.7.0",
      "version": "v5.7.0"
    },
    "author": {
      "name": "Astroport",
      "url": "https://astroport.fi/"
    },
    "deprecated": false,
    "network": "xion-testnet-2",
    "mainnet_code_id": "46",
    "deployed_by": "xion1q9lqzpc73fewqva98pwaqvezaf9vqqulw3hmmx",
    "deployed_at": "2025-04-03T19:32:45.321Z"
  },
  {
    "name": "Astroport TokenFactory Tracker",
    "description": "Astroport TokenFactory Tracker",
    "code_id": "338",
    "hash": "EB6FD3023BC44BCD20EC170EDCAB5D3B8AF54F9C2DD4D54955DF90FF14407F7A",
    "governance": "Genesis",
    "release": {
      "url": "https://github.com/astroport-fi/astroport-core/releases/tag/v5.7.0",
      "version": "v5.7.0"
    },
    "author": {
      "name": "Astroport",
      "url": "https://astroport.fi/"
    },
    "deprecated": false,
    "network": "xion-testnet-2",
    "mainnet_code_id": "47",
    "deployed_by": "xion1q9lqzpc73fewqva98pwaqvezaf9vqqulw3hmmx",
    "deployed_at": "2025-04-03T19:32:49.952Z"
  },
  {
    "name": "Talis Whitelist",
    "description": "Talis Whitelist",
    "code_id": "339",
    "hash": "4DAF64046B5044CD009817FC600F1157C3765004787C17D74EFA28C9B10DD5BB",
    "governance": "18",
    "release": {
      "url": "https://github.com/Talis-Art/talis_contracts_v2/commit/f084f5b7950f911b16090dfd38e1c06a177a1da8",
      "version": "f084f5b"
    },
    "author": {
      "name": "Talis",
      "url": "https://talis.art/"
    },
    "deprecated": false,
    "network": "xion-testnet-2",
    "mainnet_code_id": "48",
    "deployed_by": "xion1q9lqzpc73fewqva98pwaqvezaf9vqqulw3hmmx",
    "deployed_at": "2025-04-03T19:32:54.506Z"
  },
  {
    "name": "Talis Staking",
    "description": "Talis Staking",
    "code_id": "340",
    "hash": "EEAE25847EB8BAA051487616C9DB18015C574B6C2F09F037D0FEA5D055B17A05",
    "governance": "18",
    "release": {
      "url": "https://github.com/Talis-Art/talis_contracts_v2/commit/f084f5b7950f911b16090dfd38e1c06a177a1da8",
      "version": "f084f5b"
    },
    "author": {
      "name": "Talis",
      "url": "https://talis.art/"
    },
    "deprecated": false,
    "network": "xion-testnet-2",
    "mainnet_code_id": "49",
    "deployed_by": "xion1q9lqzpc73fewqva98pwaqvezaf9vqqulw3hmmx",
    "deployed_at": "2025-04-03T19:32:59.080Z"
  },
  {
    "name": "Talis Frens Proxy",
    "description": "Talis Frens Proxy",
    "code_id": "341",
    "hash": "EE8F802A7B773B718A00473CE2D039B1D062A2BD2A8484704223D72F5C43B987",
    "governance": "18",
    "release": {
      "url": "https://github.com/Talis-Art/talis_contracts_v2/commit/f084f5b7950f911b16090dfd38e1c06a177a1da8",
      "version": "f084f5b"
    },
    "author": {
      "name": "Talis",
      "url": "https://talis.art/"
    },
    "deprecated": false,
    "network": "xion-testnet-2",
    "mainnet_code_id": "50",
    "deployed_by": "xion1q9lqzpc73fewqva98pwaqvezaf9vqqulw3hmmx",
    "deployed_at": "2025-04-03T19:33:03.743Z"
  },
  {
    "name": "Talis Trading Escrow",
    "description": "Talis Trading Escrow",
    "code_id": "342",
    "hash": "88562F5F7655A19ED3C5019639EC8B0AA0F8D22A8BD7EF6E54463A5C8195C5AB",
    "governance": "18",
    "release": {
      "url": "https://github.com/Talis-Art/talis_contracts_v2/commit/f084f5b7950f911b16090dfd38e1c06a177a1da8",
      "version": "f084f5b"
    },
    "author": {
      "name": "Talis",
      "url": "https://talis.art/"
    },
    "deprecated": false,
    "network": "xion-testnet-2",
    "mainnet_code_id": "51",
    "deployed_by": "xion1q9lqzpc73fewqva98pwaqvezaf9vqqulw3hmmx",
    "deployed_at": "2025-04-03T19:33:08.445Z"
  },
  {
    "name": "Fractit",
    "description": "A protocol for the fractional ownership of NFTs",
    "code_id": "343",
    "hash": "115A20A9EFB5DFCD6F8903186BB7020AA68A117F2FE0CB0297B76EFA3B0DA9F8",
    "release": {
      "url": "https://github.com/Fractit/fractible_xion",
      "version": "b62e2bc8aa7646e73bceb07af67137c48c5a7488"
    },
    "author": {
      "name": "Fractit",
      "url": "https://fractit.com"
    },
    "governance": "21",
    "deprecated": false,
    "network": "xion-testnet-2",
    "mainnet_code_id": "52",
    "deployed_by": "xion1q9lqzpc73fewqva98pwaqvezaf9vqqulw3hmmx",
    "deployed_at": "2025-04-03T19:33:13.054Z"
  },
  {
    "name": "Fractit Inception Pass",
    "description": "Protocol for managing Fractit Inception Pass NFTs",
    "code_id": "344",
    "hash": "B33322164E02BC5D1123D84EB4D8BC96FFAC75B04B8D4856596C34D24DA7820D",
    "release": {
      "url": "https://github.com/Fractit/fractible_xion",
      "version": "2eb952db4592ea3965070c1199117927319f433b"
    },
    "author": {
      "name": "Fractit",
      "url": "https://fractit.com"
    },
    "governance": "22",
    "deprecated": false,
    "network": "xion-testnet-2",
    "mainnet_code_id": "53",
    "deployed_by": "xion1q9lqzpc73fewqva98pwaqvezaf9vqqulw3hmmx",
    "deployed_at": "2025-04-03T19:33:17.556Z"
  },
  {
    "name": "Thrive Protocol",
    "description": "First Thrive Protocol contract implementation on XION, enabling to distribute rewards achieved in Thrive XION",
    "code_id": "345",
    "hash": "455B5C3D2ED222232D56EC0384692F50A08ABF50F1DFDFA9558C97331FEC1494",
    "release": {
      "url": "https://github.com/ThriveCoin/tp-xion-reward-contract-rs",
      "version": "cd3f0e36d50f06b4f6a04511ff67bfb7b515829b"
    },
    "author": {
      "name": "Thrive Protocol",
      "url": "https://thriveprotocol.com"
    },
    "governance": "24",
    "deprecated": false,
    "network": "xion-testnet-2",
    "mainnet_code_id": "54",
    "deployed_by": "xion1q9lqzpc73fewqva98pwaqvezaf9vqqulw3hmmx",
    "deployed_at": "2025-04-03T19:33:21.976Z"
  },
  {
    "name": "MetaAccount (v3)",
    "description": "Third version of Xion's MetaAccount implementation",
    "code_id": "346",
    "hash": "6EEA0BECE8CDDC101290F5A016B866A6832E3487BDC1D620F7DFCDC407E25389",
    "governance": "26",
    "release": {
      "url": "https://github.com/burnt-labs/contracts",
      "version": "98fb64c9c4d917ba9e4b223b64558a2fd4c09ac7"
    },
    "author": {
      "name": "Burnt Labs",
      "url": "https://burnt.com"
    },
    "deprecated": false,
    "network": "xion-testnet-2",
    "mainnet_code_id": "55",
    "deployed_by": "xion1q9lqzpc73fewqva98pwaqvezaf9vqqulw3hmmx",
    "deployed_at": "2025-04-03T19:33:26.798Z"
  }
]